[
      {"pina_colada" : {
			"ingredients": [
				["White Rum", "60", "ml"],
				["Cream of Coconut", "45", "ml"],
				["Pinapple Juice", "45", "ml"],
				["Lime Juice", "30", "ml"],
				["Pinapple Wedge", "1", " Wedge"],
				["Umbrealla", "1", " Garnish"],
				["Cherry", "1", " Garnish"]
			],
			"steps": [
				"Put all ingredients in to a shaker with ice",
				"Strain in to a suitably tropical glass",
				"Add rediculous garnishes"
			],
		  	"meta": {
				"title": "Pina Colada",
				"base": "White Rum"
			}
		}
      },
      {"old_fashioned": {
			"ingredients": [
				["Angostura bitters", "4", " Dashes"],
				["Sugar Cube", "1", " Cube"],
				["Soda Water", "1", " Dash"],
				["Rye Whiskey", "60", "ml"]
			],
			"steps": [
				"Stir bitters, sugar and soda with flat end of long stiring spoon",
				"Add whiskey and ice then stir",
				"Add orange peal for garnish if desired"
			],
		  	"meta": {
				"title": "Old Fashioned",
				"base": "Rye Whiskey"
			}
		}
        },
      {"daquiri": {
			"ingredients": [
				["Simple Syrup", "25", "ml"],
				["Lime Juice", "30", "ml"],
				["White Rum", "60", "ml"]
			],
			"steps": [
				"Add ingredients to a shaker with ice",
				"Shake then strain into a glass",
				"Add a lime wedge to garnish"
			],
		  	"meta": {
				"title": "Daquiri",
				"base": "White Rum"
			}
		}
        },
	{"whiskey_smash": {
		"ingredients": [
			["Mint Leaves", "9", " Leaves"],
			["Lemon Wedge", "1", " Wedge"],
			["Simple Syrup", "25", "ml"],
			["Bourbon", "60", "ml"]
		],
		"steps": [
			"Place mint leaves in bottom of a shaker and then the lemon wedge peal side down",
			"Muddle with a rolling pin!",
			"Add small pieces of ice and shake",
			"Empty in to a glass, cover with more ice and mint to garnish"
		],
		"meta": {
			"title": "Whiskey Smash",
			"base": "Bourbon"
		}
	}
	},
	{"mojito": {
		"ingredients": [
			["White Rum", "60", "ml"],
			["Simple Syrup", "25", "ml"],
			["Mint leaves", "9", " Leaves"],
			["Lime Wedge", "4", " Wedges"],
			["Sugar Cube", "1", "ml"]
		],
		"steps": [
			"Simply mix with ice in a tall glass"
		],
		"meta": {
			"title": "Mojito",
			"base": "White Rum"
		}
	}},
	{"canchanchara": {
		"ingredients": [
			["White Rum", "45", "ml"],
			["Lime Juice", "1", " Whole"],
			["Honey Syrup", "15", "ml"],
			["Club Soda", "1", " Splash"],
			["Lime Wedge", "1", " Wedge"]
		],
		"steps": [
			"Put in a shaker with ice and whip in to shape"
		],
		"meta": {
			"title": "Canchanchara",
			"base": "White Rum"
		}
	}},
	{"banana_daquiri": {
		"ingredients": [
			["White Rum", "60", "ml"],
			["Banana Liqueur", "15", "ml"],
			["Lime Juice", "30", "ml"],
			["Demerara Syrup", "7", "ml"],
			["Banana Slice", "1", " Slice"]
		],
		"steps": [
			"Add all ingredients to a shaker with ice, shake, serve"
		],
		"meta": {
			"title": "Banana Daquiri",
			"base": "White Rum"
		}
	}},
	{"mudslide": {
		"ingredients": [
			["Vodka", "25", "ml"],
			["Kaluha", "25", "ml"],
			["Irish Cream", "25", "ml"]
		],
		"steps": [
			"Shake all ingredients with cracked ice",
			"Strain in to a glass and add chocolate curls or powder"
		],
		"meta": {
			"title": "Mudslide",
			"base": "Vodka"
		}
	}},
	{"purple_haze": {
		"ingredients": [
			["Vodka", "30", "ml"],
			["Blue Curacao", "30", "ml"],
			["Cranberry Juice", "1", " Glass"]
		],
		"steps": [
			"Mix vodka and blue curacao in a shaker",
			"Strain in to a highball glass and fill with the Cranberry Juice"
		],
		"meta": {
			"title": "Purple Haze",
			"base": "Vodka"
		}
	}},
	{"salty_dog": {
		"ingredients": [
			["Vodka", "45", "ml"],
			["Grapefruit Juice", "180", "ml"],
			["Salt", "1", " Dusting"]
		],
		"steps": [
			"Mix the Vodka and Grapefruit Juice in a shaker",
			"Dust the rim of a chilled highball glass with salt",
			"Add cracked ice and strain shaken ingredients in to glass"
		],
		"meta": {
			"title": "Salty Dog",
			"base": "Vodka"
		}
	}},
	{"pornstar": {
		"ingredients": [
			["Vanilla Vodka", "45", "ml"],
			["Passion Fruit Liqueur", "15", "ml"],
			["Passion Fruit Puree", "30", "ml"],
			["Lime Juice", "1", " Squeeze"],
			["Vanilla Simple Syrup", "15", "ml"],
			["Sparkling Wine", "60", "ml"],
			["Passion Fruit", "1", " Half"]
		],
		"steps": [
			"Add all the ingredients except the fizz to a shaker with ice",
			"Shake vigorously",
			"Strain in to a glass and add the Passion fruit garnish",
			"Serve with the Sparkling wine sidecar"
		],
		"meta": {
			"title": "Pornstar Martini",
			"base": "Vodka"
		}
	}},
	{"red_hook": {
		"ingredients": [
			["Rye Whiskey", "60", "ml"],
			["Maraschino Liqueur", "15", "ml"],
			["Punt e Mes", "15", "ml"],
			["Maraschino Cherry", "1", " Whole"]
		],
		"steps": [
			"Add all ingredients to a mixing glass with ice and stir until well-chilled.",
			"Strain in to a glass and add the cherry to garnish"
		],
		"meta": {
			"title": "Red Hook",
			"base": "Rye Whiskey"
		}
	}},
	{"none": {
		"ingredients": [
		],
		"steps": [

		],
		"meta": {
			"title": "none",
			"base": "none"
		}
	}}
]